DanaoJianyadeZidanBijishu/README.md
DanaoJianyadeZidanBijishu/__init__.py
DanaoJianyadeZidanBijishu/__main__.py
DanaoJianyadeZidanBijishu/file.epub
DanaoJianyadeZidanBijishu/index.html
DanaoJianyadeZidanBijishu/css/__init__.py
DanaoJianyadeZidanBijishu/css/annotations.css
DanaoJianyadeZidanBijishu/css/main.css
DanaoJianyadeZidanBijishu/css/normalize.css
DanaoJianyadeZidanBijishu/css/popup.css
DanaoJianyadeZidanBijishu/font/__init__.py
DanaoJianyadeZidanBijishu/font/fontello.eot
DanaoJianyadeZidanBijishu/font/fontello.svg
DanaoJianyadeZidanBijishu/font/fontello.ttf
DanaoJianyadeZidanBijishu/font/fontello.woff
DanaoJianyadeZidanBijishu/img/__init__.py
DanaoJianyadeZidanBijishu/img/annotator-glyph-sprite.png
DanaoJianyadeZidanBijishu/img/annotator-icon-sprite.png
DanaoJianyadeZidanBijishu/img/apple-touch-icon.png
DanaoJianyadeZidanBijishu/img/cancelfullscreen.png
DanaoJianyadeZidanBijishu/img/close.png
DanaoJianyadeZidanBijishu/img/fullscreen.png
DanaoJianyadeZidanBijishu/img/loader.gif
DanaoJianyadeZidanBijishu/img/menu-icon.png
DanaoJianyadeZidanBijishu/img/save.png
DanaoJianyadeZidanBijishu/img/saved.png
DanaoJianyadeZidanBijishu/img/settings-s.png
DanaoJianyadeZidanBijishu/img/settings.png
DanaoJianyadeZidanBijishu/img/star.png
DanaoJianyadeZidanBijishu/js/__init__.py
DanaoJianyadeZidanBijishu/js/epub.js
DanaoJianyadeZidanBijishu/js/epub.min.js
DanaoJianyadeZidanBijishu/js/epub.min.map
DanaoJianyadeZidanBijishu/js/hooks.min.js
DanaoJianyadeZidanBijishu/js/hooks.min.map
DanaoJianyadeZidanBijishu/js/reader.js
DanaoJianyadeZidanBijishu/js/reader.js.map
DanaoJianyadeZidanBijishu/js/reader.min.js
DanaoJianyadeZidanBijishu/js/reader.min.map
DanaoJianyadeZidanBijishu/js/hooks/__init__.py
DanaoJianyadeZidanBijishu/js/hooks/extensions/__init__.py
DanaoJianyadeZidanBijishu/js/hooks/extensions/highlight.js
DanaoJianyadeZidanBijishu/js/libs/__init__.py
DanaoJianyadeZidanBijishu/js/libs/jquery.min.js
DanaoJianyadeZidanBijishu/js/libs/localforage.min.js
danao_jianyade_zidan_bijishu-2022.10.15.0.dist-info/METADATA
danao_jianyade_zidan_bijishu-2022.10.15.0.dist-info/WHEEL
danao_jianyade_zidan_bijishu-2022.10.15.0.dist-info/entry_points.txt
danao_jianyade_zidan_bijishu-2022.10.15.0.dist-info/top_level.txt
danao_jianyade_zidan_bijishu-2022.10.15.0.dist-info/RECORD
